{"ast":null,"code":"var vocabItem = document.getElementsByClassName('vocab__item');\nvocabItem.おんｃぃｃ;","map":{"version":3,"sources":["/Users/koshifutami/GoogleDrive/projects/uchiben/app/javascript/vocab/index.js"],"names":["vocabItem","document","getElementsByClassName","おんｃぃｃ"],"mappings":"AAAA,IAAIA,SAAS,GAAGC,QAAQ,CAACC,sBAAT,CAAgC,aAAhC,CAAhB;AACAF,SAAS,CAACG,KAAV","sourcesContent":["let vocabItem = document.getElementsByClassName('vocab__item');\nvocabItem.おんｃぃｃ"]},"metadata":{},"sourceType":"module"}